Workbook
Name aporte: Invest!$C$18
Name patrimonio: Invest!$C$21
Name qtd_anos: Invest!$C$19
Name rendimento_carteira: Invest!$C$14
Name salario: Invest!$C$13
Name sugestao_investimento: Invest!$C$15
Name taxa_mensal: Invest!$C$20

Sheet Invest
B12: CONFIGURAÇÕES
B13: Salário | C13: 2000
B14: Dividend Yield Mensal | C14: 0.006
B15: Sugestão de Investimento (30%) | C15: =C13*30% -> 600
B17: INVESTIMENTO MENSAL
B18: Quanto investir por mês? | C18: 200
B19: Por quantos anos? | C19: 5
B20: Rentabilidade Total (Cotas + Dividendos) | C20: 0.01079
B21: Patrimônio acumulado? | C21: =FV(taxa_mensal,qtd_anos*12,aporte*-1) -> 16755.383
B22: Dividendos mensais? | C22: =patrimonio*rendimento_carteira -> 100.5323
B24: CENÁRIOS | D24: DIVIDENDOS
A25: 2 | B25: Quanto em 2 anos? | C25: =FV($C$20,$A25*12,$C$18*-1) -> 5445.5255 | D25: =C25*rendimento_carteira -> 32.673153
A26: 5 | B26: Quanto em 5 anos? | C26: =FV($C$20,$A26*12,$C$18*-1) -> 16755.383 | D26: =C26*rendimento_carteira -> 100.5323
A27: 10 | B27: Quanto em 10 anos? | C27: =FV($C$20,$A27*12,$C$18*-1) -> 48656.843 | D27: =C27*rendimento_carteira -> 291.94106
A28: 20 | B28: Quanto em 20 anos? | C28: =FV($C$20,$A28*12,$C$18*-1) -> 225039.68 | D28: =C28*rendimento_carteira -> 1350.2381
A29: 30 | B29: Quanto em 30 anos? | C29: =FV($C$20,$A29*12,$C$18*-1) -> 864433.93 | D29: =C29*rendimento_carteira -> 5186.6036
B32: SELECIONA SEU PERFIL | C32: Agressivo
B33: VALOR A SER INVESTIDO POR MÊS | C33: =aporte -> 200
B35: TIPOS DE FII | C35: Percentual Sugerido | D35: Valores
B36: PAPEL | C36: =VLOOKUP($C$32&"-"&B36,'Planilha de Apoio'!$A:$D,4,FALSE) -> 0.5 | D36: =$C$33*C36 -> 100
B37: TIJOLO | C37: =VLOOKUP($C$32&"-"&B37,'Planilha de Apoio'!$A:$D,4,FALSE) -> 0.1 | D37: =$C$33*C37 -> 20
B38: HÍBRIDOS | C38: =VLOOKUP($C$32&"-"&B38,'Planilha de Apoio'!$A:$D,4,FALSE) -> 0.05 | D38: =$C$33*C38 -> 10
B39: FOFs | C39: =VLOOKUP($C$32&"-"&B39,'Planilha de Apoio'!$A:$D,4,FALSE) -> 0.05 | D39: =$C$33*C39 -> 10
B40: DESENVOLVIMENTO | C40: =VLOOKUP($C$32&"-"&B40,'Planilha de Apoio'!$A:$D,4,FALSE) -> 0.2 | D40: =$C$33*C40 -> 40
B41: HOTELARIAS | C41: =VLOOKUP($C$32&"-"&B41,'Planilha de Apoio'!$A:$D,4,FALSE) -> 0.1 | D41: =$C$33*C41 -> 20
D42: =SUM(D36:D41) -> 200

Sheet Planilha de Apoio
A2: CHAVE | B2: PERFIL | C2: TIPO DE FII | D2: %
A3: =B3&"-"&C3 -> Conservador-PAPEL | B3: Conservador | C3: PAPEL | D3: 0.3
A4: =B4&"-"&C4 -> Conservador-TIJOLO | B4: Conservador | C4: TIJOLO | D4: 0.5
A5: =B5&"-"&C5 -> Conservador-HÍBRIDOS | B5: Conservador | C5: HÍBRIDOS | D5: 0.1
A6: =B6&"-"&C6 -> Conservador-FOFs | B6: Conservador | C6: FOFs | D6: 0.1
A7: =B7&"-"&C7 -> Conservador-DESENVOLVIMENTO | B7: Conservador | C7: DESENVOLVIMENTO | D7: 0
A8: =B8&"-"&C8 -> Conservador-HOTELARIAS | B8: Conservador | C8: HOTELARIAS | D8: 0
A9: =B9&"-"&C9 -> Moderado-PAPEL | B9: Moderado | C9: PAPEL | D9: 0.32
A10: =B10&"-"&C10 -> Moderado-TIJOLO | B10: Moderado | C10: TIJOLO | D10: 0.4
A11: =B11&"-"&C11 -> Moderado-HÍBRIDOS | B11: Moderado | C11: HÍBRIDOS | D11: 0.08
A12: =B12&"-"&C12 -> Moderado-FOFs | B12: Moderado | C12: FOFs | D12: 0.1
A13: =B13&"-"&C13 -> Moderado-DESENVOLVIMENTO | B13: Moderado | C13: DESENVOLVIMENTO | D13: 0.05
A14: =B14&"-"&C14 -> Moderado-HOTELARIAS | B14: Moderado | C14: HOTELARIAS | D14: 0.05
... A20: =B20&"-"&C20 -> Agressivo-HOTELARIAS | B20: Agressivo | C20: HOTELARIAS | D20: 0.1
